verilog_final/fir4rca.sv
//Transpose CLA architecture


module fir4rca #(parameter w=16)(
  input                      clk,
                             reset,
  input         [w-1:0] a,
  output logic  [w+1:0] s);
// delay pipeline for input a

//Pipeline for inputs
logic [w-1:0] ar;

//Pipeline for sums
logic [w:0]     sum1;
logic [w:0]     sum1r;
logic [w+1:0]   sum2;
logic [w+1:0]   sum2r;
logic [w+1:0]   sum3;

// RIPPLE CARRY ADDER LOGIC

  logic         [w:0] cla1_o,  cla2_o;
  logic         [w:0] rca1_co, rca2_co;

  logic         [w+1:0] sum;

// START OF CLA
logic [w-1:0] p1;
logic [w-1:0] g1;
logic [w:0] c1;
logic [w-1:0] cla1_s;

logic [w:0] p2;
logic [w:0] g2;
logic [w+1:0] c2;
logic [w:0] cr2;
logic [w:0] cla2_s;
   
logic [w+1:0]   dr3;
logic [w+1:0] p3;
logic [w+1:0] g3;
logic [w+2:0] c3;
logic [w+1:0]   cla3_s;
 
always_comb begin
    c1[0] = 1'b0;
    for (int i=0; i<w; i++) begin
        p1[i] = ar[i] ^ a[i];
        g1[i] = ar[i] & a[i];
        c1[i+1] = g1[i] | ( p1[i] & c1[i] );
        cla1_s[i] = p1[i] ^ c1[i];
    end
    sum1 = {c1[w],cla1_s};
end

always_comb begin
    c2[0] = 1'b0;
    cr2 = {1'b0,a};
    for (int i=0; i<w+1; i++) begin
        p2[i] = cr2[i] ^ sum1r[i];
        g2[i] = cr2[i] & sum1r[i];
        c2[i+1] = g2[i] | ( p2[i] & c2[i] );
        cla2_s[i] = p2[i] ^ c2[i];
    end
    sum2 = {c2[w+1],cla2_s};
end

always_comb begin
    c3[0] = 1'b0;
    dr3 = {2'b00,a};
    for (int i=0; i<w+2; i++) begin
        p3[i] = sum2r[i] ^ dr3[i];
        g3[i] = sum2r[i] & dr3[i];
        c3[i+1] = g3[i] | ( p3[i] & c3[i] );
        cla3_s[i] = p3[i] ^ c3[i];
    end
end

always_comb begin
    sum = cla3_s;
end
 
// START OF CLA

// sequential logic -- standardized for everyone
always_ff @(posedge clk)			// or just always -- always_ff tells tools you intend D flip flops
    if(reset) begin					// reset forces all registers to 0 for clean start of test
        ar <= 'b0;
        sum1r <= 'b0;
        sum2r <= 'b0;
        s  <= 'b0;
    end
    else begin					    // normal operation -- Dffs update on posedge clk
        ar <= a;
        sum1r <= sum1;
        sum2r <= sum2;
        s  <= sum; 
    end

endmodule

verilog_old/project_tb2_u.sv
// testbench for 4-tap, w-bit, unsigned averaging FIR filter
// ECE260A Lab 3 assignment   2019
// change parameter w to experiment wih wider operand vectors, such as 16 bits
`timescale 1ns/1ps

module project_tb2_u;
  parameter           w = 4;
  logic               clk = 'b0,			          
                      reset = 'b1;	  // active high
  logic  [w-1:0] a; 	              // unsigned operands
  wire   [w+1:0] s;                   // sum output from DUT
  wire signed[w+2:0] dif1;   	      // diff. between theoretical and actual rums
  logic	 [w+1:0] s_b1;    	          // "golden" sum output
  logic  [w-1:0] ar, 				  // delays of input a -- parallels actual pipeline
                 br,				  //   in DUT
                 cr,
                 dr;	              // operand tapped delay line in testbench	

// device under test goes here
// choose "tree," "cascade," "CSA," or other topology
//  fir4rca_cas_u #(.w(w)) f1(.*);
fir4rca #(.w(w)) f1(.*);
//  fir4rca_u #(.w(w)) f1(.*);

  always begin			           	  // tick ... tock 
  #5ns clk = 'b1;
	#5ns clk = 'b0;
  end

// series of 25 sets of random operands
  initial begin
    $display("a   s  s_b  diff");
    #10ns reset = '0;
	for(int i = 0; i < 10; i++) begin
	  a   = $random;// 2**(i/4);//$random;
	  #8ns $displayh(a,,,,,s,,,,s_b1,,,,dif1);
	  #2ns;
	end  
    #50ns $stop;
  end

  always @(posedge clk) 
    if(reset) begin :rst
	  ar  <= 'b0;
	  br  <= 'b0;
	  cr  <= 'b0;
	  dr  <= 'b0;
	  s_b1<= 'b0;
	end  :rst
	else begin :run
      ar  <= a;						  // match DUT's input pipe reg. delay
      br  <= ar;
      cr  <= br;
      dr  <= cr;
      s_b1 <= ar+br+cr+dr;			 // purely behavioral description of function
    end :run

  assign dif1 = s - s_b1;

initial begin
  $dumpfile("waves.vcd");
  $dumpvars(0, project_tb2_u);
end

endmodule

waves.vcd
$date
	Tue Dec  7 12:14:35 2021
$end
$version
	Icarus Verilog
$end
$timescale
	1ps
$end
$scope module project_tb2_u $end
$var wire 6 ! s [5:0] $end
$var wire 7 " dif1 [6:0] $end
$var reg 4 # a [3:0] $end
$var reg 4 $ ar [3:0] $end
$var reg 4 % br [3:0] $end
$var reg 1 & clk $end
$var reg 4 ' cr [3:0] $end
$var reg 4 ( dr [3:0] $end
$var reg 1 ) reset $end
$var reg 6 * s_b1 [5:0] $end
$scope module f1 $end
$var wire 4 + a [3:0] $end
$var wire 1 & clk $end
$var wire 1 ) reset $end
$var reg 4 , ar [3:0] $end
$var reg 5 - c1 [4:0] $end
$var reg 6 . c2 [5:0] $end
$var reg 7 / c3 [6:0] $end
$var reg 4 0 cla1_s [3:0] $end
$var reg 5 1 cla2_s [4:0] $end
$var reg 6 2 cla3_s [5:0] $end
$var reg 5 3 cr2 [4:0] $end
$var reg 6 4 dr3 [5:0] $end
$var reg 4 5 g1 [3:0] $end
$var reg 5 6 g2 [4:0] $end
$var reg 6 7 g3 [5:0] $end
$var reg 4 8 p1 [3:0] $end
$var reg 5 9 p2 [4:0] $end
$var reg 6 : p3 [5:0] $end
$var reg 6 ; s [5:0] $end
$var reg 6 < sum [5:0] $end
$var reg 5 = sum1 [4:0] $end
$var reg 5 > sum1r [4:0] $end
$var reg 6 ? sum2 [5:0] $end
$var reg 6 @ sum2r [5:0] $end
$scope begin $ivl_for_loop0 $end
$var integer 32 A i [31:0] $end
$upscope $end
$scope begin $ivl_for_loop1 $end
$var integer 32 B i [31:0] $end
$upscope $end
$scope begin $ivl_for_loop2 $end
$var integer 32 C i [31:0] $end
$upscope $end
$upscope $end
$scope begin $ivl_for_loop3 $end
$var integer 32 D i [31:0] $end
$upscope $end
$scope begin rst $end
$upscope $end
$scope begin run $end
$upscope $end
$upscope $end
$enddefinitions $end
#0
$dumpvars
b0 D
b110 C
b101 B
b100 A
bx @
bx ?
bx >
bx =
bx <
bx ;
bx :
bx 9
bx 8
b0xxxx 7
b0xxxx 6
bx 5
b0xxxx 4
b0xxxx 3
bx 2
bx 1
bx 0
bx0 /
bx0 .
bx0 -
bx ,
bx +
bx *
1)
bx (
bx '
0&
bx %
bx $
bx #
bx "
bx !
$end
#5000
b0xxxx <
b0xxxx 2
b0xxxx :
b0 /
b0 7
b110 C
b0xxxx ?
b0xxxx 1
b0xxxx 9
b0 .
b0 6
b101 B
b0xxxx =
b0 -
b0 5
b100 A
b0 "
b0 *
b0 (
b0 '
b0 %
b0 $
b0 !
b0 ;
b0 @
b0 >
b0 ,
1&
#10000
b100 <
b100 2
b100 :
b110 C
b100 4
b100 ?
b100 1
b100 9
b101 B
b100 3
b100 =
b100 0
b100 8
b100 A
0&
b100 #
b100 +
0)
#15000
b1000 <
b1000 2
b1000 /
b100 7
b0 :
b110 C
b1000 ?
b1000 1
b1000 .
b100 6
b0 9
b101 B
b1000 =
b1000 0
b1000 -
b100 5
b0 8
b100 A
b100 $
b100 "
b100 !
b100 ;
b100 @
b100 >
b100 ,
1&
#20000
b101 <
b0 /
b0 7
b101 2
b101 :
b110 C
b1 4
b101 ?
b0 .
b0 6
b101 1
b101 9
b101 B
b1 3
b101 =
b0 -
b0 5
b101 0
b101 8
b100 A
b1 #
b1 +
b1 D
0&
#25000
b110 <
b110 2
b10 /
b1 7
b100 :
b110 C
b110 ?
b110 1
b10 .
b1 6
b100 9
b101 B
b10 =
b10 0
b10 -
b1 5
b0 8
b100 A
b100 *
b100 %
b1 $
b1 "
b101 !
b101 ;
b101 @
b101 >
b1 ,
1&
#30000
b1110 <
b1110 2
b1100 :
b110 C
b1001 4
b1110 ?
b1110 1
b1100 9
b101 B
b1001 3
b1010 =
b1010 0
b1000 8
b100 A
b1001 #
b1001 +
b10 D
0&
#35000
b10111 <
b10111 2
b10000 /
b1000 7
b111 :
b110 C
b10011 ?
b10011 1
b10000 .
b1000 6
b11 9
b101 B
b10010 =
b10 0
b10010 -
b1001 5
b0 8
b100 A
b101 *
b100 '
b1 %
b1001 $
b1001 "
b1110 !
b1110 ;
b1110 @
b1010 >
b1001 ,
1&
#40000
b10001 <
b10001 2
b11100 /
b10 7
b1101 :
b110 C
b11 4
b1101 ?
b1101 1
b100 .
b10 6
b1001 9
b101 B
b11 3
b1100 =
b1 5
b1100 0
b110 -
b1010 8
b100 A
b11 #
b11 +
b11 D
0&
#45000
b10000 <
b10000 2
b11110 /
b1 7
b1110 :
b110 C
b1111 ?
b1111 1
b0 .
b0 6
b1111 9
b101 B
b110 =
b110 0
b11 5
b0 8
b100 A
b1110 *
b100 (
b1 '
b1001 %
b11 $
b11 "
b10001 !
b10001 ;
b1101 @
b1100 >
b11 ,
1&
#50000
b11010 <
b1101 7
b11010 2
b11010 /
b0 :
b110 C
b1101 4
b11001 ?
b11000 .
b1100 6
b11001 1
b1 9
b101 B
b1101 3
b10000 =
b11110 -
b0 0
b1 5
b1110 8
b100 A
b1101 #
b1101 +
b100 D
0&
#55000
b100110 <
b100110 2
b110010 /
b1001 7
b10100 :
b110 C
b11101 ?
b11101 1
b0 .
b0 6
b11101 9
b101 B
b11010 =
b1101 5
b1010 0
b11010 -
b0 8
b100 A
b10001 *
b1 (
b1001 '
b11 %
b1101 $
b1001 "
b11010 !
b11010 ;
b11001 @
b10000 >
b1101 ,
1&
#60000
b101 D
0&
#65000
b101010 <
b101010 2
b111010 /
b1101 7
b10000 :
b110 C
b100 A
b100111 ?
b110000 .
b1000 6
b111 1
b10111 9
b101 B
b11010 *
b1001 (
b11 '
b1101 %
b1100 "
b100110 !
b100110 ;
b11101 @
b11010 >
1&
#70000
b100010 <
b100010 2
b101 7
b11000 :
b110 C
b101 4
b11111 ?
b11111 1
b0 .
b0 6
b11111 9
b101 B
b101 3
b10010 =
b10 0
b101 5
b1000 8
b100 A
b101 #
b101 +
b110 D
0&
#75000
b100100 <
b100100 2
b111110 /
b11010 :
b110 C
b10111 ?
b10111 1
b10111 9
b101 B
b1010 =
b1010 0
b1010 -
b0 8
b100 A
b100110 *
b11 (
b1101 '
b101 $
b1111100 "
b100010 !
b100010 ;
b11111 @
b10010 >
b101 ,
1&
#80000
b100001 <
b100001 2
b111100 /
b10 7
b11101 :
b110 C
b10 4
b10100 ?
b100 .
b10 6
b10100 1
b10000 9
b101 B
b10 3
b111 =
b111 0
b0 -
b0 5
b111 8
b100 A
b10 #
b10 +
b111 D
0&
#85000
b10110 <
b0 /
b0 7
b10110 2
b10110 :
b110 C
b1001 ?
b1100 .
b1001 1
b101 9
b101 B
b100 =
b100 -
b10 5
b100 0
b0 8
b100 A
b100010 *
b1101 (
b101 %
b10 $
b1111111 "
b100001 !
b100001 ;
b10100 @
b111 >
b10 ,
1&
#90000
b10101 <
b10101 2
b10101 :
b110 C
b1 4
b1000 ?
b1000 1
b1110 .
b1 6
b110 9
b101 B
b1 3
b11 =
b0 -
b0 5
b11 0
b11 8
b100 A
b1 #
b1 +
b1000 D
0&
#95000
b1001 <
b1001 2
b1001 :
b110 C
b100 ?
b100 1
b110 .
b10 9
b101 B
b10 =
b10 0
b10 -
b1 5
b0 8
b100 A
b100001 *
b101 '
b10 %
b1 $
b1110100 "
b10101 !
b10101 ;
b1000 @
b11 >
b1 ,
1&
#100000
b10101 <
b10000 /
b1000 7
b10101 2
b101 :
b110 C
b1101 4
b10000 ?
b10000 1
b11110 .
b1110 9
b101 B
b1101 3
b1110 =
b1110 0
b1100 8
b100 A
b1101 #
b1101 +
b1001 D
0&
#105000
b11101 <
b11101 2
b0 /
b0 7
b11101 :
b110 C
b11011 ?
b11011 1
b11000 .
b1100 6
b11 9
b101 B
b11010 =
b1010 0
b11010 -
b1101 5
b0 8
b100 A
b0 "
b10101 *
b101 (
b10 '
b1 %
b1101 $
b10000 @
b1110 >
b1101 ,
1&
#110000
b1010 D
0&
#115000
b101000 <
b101000 2
b111110 /
b1001 7
b10110 :
b110 C
b100 A
b100111 ?
b111 1
b110000 .
b1000 6
b10111 9
b101 B
b10 (
b1 '
b1101 %
b1000 "
b11101 !
b11101 ;
b11011 @
b11010 >
1&
#120000
0&
#125000
b110100 <
b100 A
b101 B
b11110 /
b110100 2
b101 7
b101010 :
b110 C
b11101 *
b1 (
b1101 '
b1011 "
b101000 !
b101000 ;
b100111 @
1&
#130000
0&
#135000
b101000 *
b1101 (
b1100 "
b110100 !
b110100 ;
1&
#140000
0&
#145000
b0 "
b110100 *
1&
